Workbook

Sheet Floor Parameters
A1: Zava Retail Channel Margin Floor
A2: Doc. TBL-PRC-2026-03 v2.1 Effective 2026-07-01 Owner: Pricing Governance
A4: Parameter | B4: Value | C4: Description
A5: Standard price | B5: 1000 | C5: Anniversary Hero Bundle; same in all channels
A6: Unit cost | B6: 640 | C6: Standard cost
A7: Margin floor | B7: 0.18 | C7: On selling price; POL-PRC-2026-03 section 3
A10: Channel | B10: Code | C10: Margin floor | D10: Routine discount cap | E10: Channel description
A11: Online | B11: WEB | C11: =$B$7 | D11: 0.15 | E11: Zava online store
A12: Store | B12: STR | C12: =$B$7 | D12: 0.15 | E12: Company-operated stores
A13: Franchise | B13: FRN | C13: =$B$7 | D13: 0.15 | E13: Franchise stores
A15: Note: discounts above the routine cap must be registered in the Discount Exception Log. Whether a supplier subsidy applies is determined by each agreement; this table assumes none.

Sheet Margin Calculator
A1: Margin Calculator
A2: Enter channel, discount rate and subsidy (per the subsidy agreement); other columns calculate automatically
A4: Exception ID | B4: Channel | C4: Discount | D4: Std price | E4: Net price | F4: Unit cost | G4: Subsidy (per unit) | H4: Margin amount | I4: Gross margin | J4: Floor | K4: Gap (pt) | L4: Result
D5: =IF(C5="","",'Floor Parameters'!$B$5) | E5: =IF(C5="","",D5*(1-C5)) | F5: =IF(C5="","",'Floor Parameters'!$B$6) | H5: =IF(C5="","",E5-F5+N(G5)) | I5: =IF(C5="","",H5/E5) | J5: =IF(C5="","",'Floor Parameters'!$B$7) | K5: =IF(C5="","",(I5-J5)*100) | L5: =IF(C5="","",IF(I5>=J5,"Compliant","Breach"))
D6: =IF(C6="","",'Floor Parameters'!$B$5) | E6: =IF(C6="","",D6*(1-C6)) | F6: =IF(C6="","",'Floor Parameters'!$B$6) | H6: =IF(C6="","",E6-F6+N(G6)) | I6: =IF(C6="","",H6/E6) | J6: =IF(C6="","",'Floor Parameters'!$B$7) | K6: =IF(C6="","",(I6-J6)*100) | L6: =IF(C6="","",IF(I6>=J6,"Compliant","Breach"))
D7: =IF(C7="","",'Floor Parameters'!$B$5) | E7: =IF(C7="","",D7*(1-C7)) | F7: =IF(C7="","",'Floor Parameters'!$B$6) | H7: =IF(C7="","",E7-F7+N(G7)) | I7: =IF(C7="","",H7/E7) | J7: =IF(C7="","",'Floor Parameters'!$B$7) | K7: =IF(C7="","",(I7-J7)*100) | L7: =IF(C7="","",IF(I7>=J7,"Compliant","Breach"))
D8: =IF(C8="","",'Floor Parameters'!$B$5) | E8: =IF(C8="","",D8*(1-C8)) | F8: =IF(C8="","",'Floor Parameters'!$B$6) | H8: =IF(C8="","",E8-F8+N(G8)) | I8: =IF(C8="","",H8/E8) | J8: =IF(C8="","",'Floor Parameters'!$B$7) | K8: =IF(C8="","",(I8-J8)*100) | L8: =IF(C8="","",IF(I8>=J8,"Compliant","Breach"))
D9: =IF(C9="","",'Floor Parameters'!$B$5) | E9: =IF(C9="","",D9*(1-C9)) | F9: =IF(C9="","",'Floor Parameters'!$B$6) | H9: =IF(C9="","",E9-F9+N(G9)) | I9: =IF(C9="","",H9/E9) | J9: =IF(C9="","",'Floor Parameters'!$B$7) | K9: =IF(C9="","",(I9-J9)*100) | L9: =IF(C9="","",IF(I9>=J9,"Compliant","Breach"))
D10: =IF(C10="","",'Floor Parameters'!$B$5) | E10: =IF(C10="","",D10*(1-C10)) | F10: =IF(C10="","",'Floor Parameters'!$B$6) | H10: =IF(C10="","",E10-F10+N(G10)) | I10: =IF(C10="","",H10/E10) | J10: =IF(C10="","",'Floor Parameters'!$B$7) | K10: =IF(C10="","",(I10-J10)*100) | L10: =IF(C10="","",IF(I10>=J10,"Compliant","Breach"))
D11: =IF(C11="","",'Floor Parameters'!$B$5) | E11: =IF(C11="","",D11*(1-C11)) | F11: =IF(C11="","",'Floor Parameters'!$B$6) | H11: =IF(C11="","",E11-F11+N(G11)) | I11: =IF(C11="","",H11/E11) | J11: =IF(C11="","",'Floor Parameters'!$B$7) | K11: =IF(C11="","",(I11-J11)*100) | L11: =IF(C11="","",IF(I11>=J11,"Compliant","Breach"))
D12: =IF(C12="","",'Floor Parameters'!$B$5) | E12: =IF(C12="","",D12*(1-C12)) | F12: =IF(C12="","",'Floor Parameters'!$B$6) | H12: =IF(C12="","",E12-F12+N(G12)) | I12: =IF(C12="","",H12/E12) | J12: =IF(C12="","",'Floor Parameters'!$B$7) | K12: =IF(C12="","",(I12-J12)*100) | L12: =IF(C12="","",IF(I12>=J12,"Compliant","Breach"))

Sheet Revision Log
A1: Revision Log
A3: Version | B3: Effective | C3: Margin floor | D3: Description
A4: v2.1 | B4: 2026-07-01 | C4: 0.18 | D4: Current version
A5: v2.0 | B5: 2025-07-01 | C5: 0.16 | D5: Superseded; franchise channel added
A6: v1.0 | B6: 2024-07-01 | C6: 0.15 | D6: Superseded
